truss/__init__.py
truss/linear_elastic.py
truss/plot.py
truss/truss.py
pytruss-0.0.1.dist-info/LICENSE
pytruss-0.0.1.dist-info/METADATA
pytruss-0.0.1.dist-info/WHEEL
pytruss-0.0.1.dist-info/top_level.txt
pytruss-0.0.1.dist-info/RECORD
